service_helper.py
systemd_shortcuts-0.0.2.dist-info/LICENSE
systemd_shortcuts-0.0.2.dist-info/METADATA
systemd_shortcuts-0.0.2.dist-info/WHEEL
systemd_shortcuts-0.0.2.dist-info/entry_points.txt
systemd_shortcuts-0.0.2.dist-info/top_level.txt
systemd_shortcuts-0.0.2.dist-info/RECORD
