Metadata-Version: 2.1
Name: systemd-shortcuts
Version: 0.0.2
Summary: A small utility to have some common systemd/journalctl shortcuts
Requires-Python: >=3.9
License-File: LICENSE
Requires-Dist: click>=8.1.7
Requires-Dist: python-dotenv>=1.0.1
